csp_discord/__init__.py
csp_discord/tests/test_all.py
csp_discord-1.1.0.dist-info/METADATA
csp_discord-1.1.0.dist-info/WHEEL
csp_discord-1.1.0.dist-info/licenses/LICENSE
csp_discord-1.1.0.dist-info/RECORD
